modelmanager_api/modelmanager_api.py
modelmanager_api/api_assets/model_assets/model_file.csv
modelmanager_api/api_assets/model_assets/scoring_file.csv
modelmanager_api/api_assets/model_assets/submissionsample.csv
modelmanager_api/api_assets/model_assets/test.csv
modelmanager_api/api_assets/model_assets/train.csv
modelmanager_api/api_assets/model_assets/truth.csv
modelmanager_api/api_assets/project_assets/banner.jpg
modelmanager_api/api_assets/project_assets/image.jpg
modelmanager_api/api_assets/project_assets/thumbnail.jpg
modelmanager_api/example_scripts/add_model.py
modelmanager_api/example_scripts/add_project.py
modelmanager_api/example_scripts/delete_model.py
modelmanager_api/example_scripts/delete_project.py
modelmanager_api/example_scripts/update_model.py
modelmanager_api/example_scripts/update_project.py
modelmanager_api-2.0.5.dist-info/METADATA
modelmanager_api-2.0.5.dist-info/RECORD
modelmanager_api-2.0.5.dist-info/WHEEL
modelmanager_api-2.0.5.dist-info/top_level.txt
