Metadata-Version: 2.1
Name: modelmanager-api
Version: 2.0.5
Summary: Modelmanager api
Home-page: UNKNOWN
Author: falcon
License: MIT
Platform: UNKNOWN
Classifier: Programming Language :: Python :: 3
Classifier: License :: OSI Approved :: MIT License
Classifier: Operating System :: OS Independent
Requires-Dist: requests
